urlnormalizer/__init__.py
urlnormalizer/constants.py
urlnormalizer/normalizer.py
urlnormalizer/query.py
urlnormalizer/utils.py
urlnormalizer/validator.py
urlnormalizer-1.2.5.dist-info/LICENSE
urlnormalizer-1.2.5.dist-info/METADATA
urlnormalizer-1.2.5.dist-info/WHEEL
urlnormalizer-1.2.5.dist-info/top_level.txt
urlnormalizer-1.2.5.dist-info/RECORD
