Metadata-Version: 2.1
Name: urlnormalizer
Version: 1.2.5
Summary: Normalize URLs. Mostly useful for deduplicating HTTP URLs.
Home-page: https://github.com/alephdata/urlnormalizer
Author: Tarashish Mishra
Author-email: sunu@sunu.in
License: MIT
Platform: UNKNOWN
Classifier: Development Status :: 3 - Alpha
Classifier: Intended Audience :: Developers
Classifier: License :: OSI Approved :: MIT License
Classifier: Operating System :: OS Independent
Classifier: Programming Language :: Python :: 2
Classifier: Programming Language :: Python :: 3
Requires-Dist: six
Requires-Dist: chardet
